LICENSE
power_cache/__init__.py
power_cache/async_memoize.py
power_cache/key.py
power_cache/lru.py
power_cache/memoize.py
power_cache/py.typed
power_cache/ttl.py
power_cache-0.1.1.dist-info/LICENSE
power_cache-0.1.1.dist-info/WHEEL
power_cache-0.1.1.dist-info/METADATA
power_cache-0.1.1.dist-info/RECORD
