Metadata-Version: 2.1
Name: power-cache
Version: 0.1.1
Summary: Simple (but powerful) Caching Tools
Home-page: https://github.com/Coder-Spirit/power_cache
License: MIT
Keywords: cache,lru,ttl,decorator
Author: Andres Correa Casablanca
Author-email: castarco@coderspirit.xyz
Requires-Python: >=3.7,<4.0
Classifier: Environment :: Console
Classifier: Environment :: Other Environment
Classifier: Environment :: Web Environment
Classifier: Intended Audience :: Developers
Classifier: License :: OSI Approved :: MIT License
Classifier: Operating System :: OS Independent
Classifier: Programming Language :: Python :: 3
Classifier: Programming Language :: Python :: 3.7
Classifier: Programming Language :: Python :: 3.8
Classifier: Programming Language :: Python :: 3.9
Classifier: Topic :: Software Development :: Libraries :: Python Modules
Classifier: Topic :: Utilities
Classifier: Typing :: Typed
Project-URL: Repository, https://github.com/Coder-Spirit/power_cache
